LICENSE
MANIFEST.in
README.rst
setup.py
django_fortune.egg-info/PKG-INFO
django_fortune.egg-info/SOURCES.txt
django_fortune.egg-info/dependency_links.txt
django_fortune.egg-info/requires.txt
django_fortune.egg-info/top_level.txt
fortune/__init__.py
fortune/models.py
fortune/serializers.py
fortune/tests.py
fortune/urls.py
fortune/utils.py
fortune/views.py
fortune/fortunes/art
fortune/fortunes/art.dat
fortune/fortunes/ascii-art
fortune/fortunes/ascii-art.dat
fortune/fortunes/computers
fortune/fortunes/computers.dat
fortune/fortunes/cookie
fortune/fortunes/cookie.dat
fortune/fortunes/definitions
fortune/fortunes/definitions.dat
fortune/fortunes/drugs
fortune/fortunes/drugs.dat
fortune/fortunes/education
fortune/fortunes/education.dat
fortune/fortunes/ethnic
fortune/fortunes/ethnic.dat
fortune/fortunes/food
fortune/fortunes/food.dat
fortune/fortunes/fortunes
fortune/fortunes/fortunes.dat
fortune/fortunes/goedel
fortune/fortunes/goedel.dat
fortune/fortunes/humorists
fortune/fortunes/humorists.dat
fortune/fortunes/kids
fortune/fortunes/kids.dat
fortune/fortunes/law
fortune/fortunes/law.dat
fortune/fortunes/linuxcookie
fortune/fortunes/linuxcookie.dat
fortune/fortunes/literature
fortune/fortunes/literature.dat
fortune/fortunes/love
fortune/fortunes/love.dat
fortune/fortunes/magic
fortune/fortunes/magic.dat
fortune/fortunes/medicine
fortune/fortunes/medicine.dat
fortune/fortunes/men-women
fortune/fortunes/men-women.dat
fortune/fortunes/miscellaneous
fortune/fortunes/miscellaneous.dat
fortune/fortunes/news
fortune/fortunes/news.dat
fortune/fortunes/people
fortune/fortunes/people.dat
fortune/fortunes/pets
fortune/fortunes/pets.dat
fortune/fortunes/platitudes
fortune/fortunes/platitudes.dat
fortune/fortunes/politics
fortune/fortunes/politics.dat
fortune/fortunes/riddles
fortune/fortunes/riddles.dat
fortune/fortunes/science
fortune/fortunes/science.dat
fortune/fortunes/songs-poems
fortune/fortunes/songs-poems.dat
fortune/fortunes/sports
fortune/fortunes/sports.dat
fortune/fortunes/startrek
fortune/fortunes/startrek.dat
fortune/fortunes/translate-me
fortune/fortunes/translate-me.dat
fortune/fortunes/wisdom
fortune/fortunes/wisdom.dat
fortune/fortunes/work
