Metadata-Version: 1.1
Name: django-fortune
Version: 1.1.1
Summary: A Django template-tag for fortunes.
Home-page: https://github.com/rerb/django-fortune
Author: Robert Erb
Author-email: bob.erb@gmail.com
License: GPL3
Keywords: django fortune
Platform: UNKNOWN
Classifier: Environment :: Web Environment
Classifier: Intended Audience :: Developers
Classifier: License :: OSI Approved :: GNU General Public License (GPL)
Classifier: Operating System :: OS Independent
Classifier: Programming Language :: Python :: 2
Classifier: Programming Language :: Python :: 2.7
Classifier: Programming Language :: Python :: 3
Classifier: Programming Language :: Python :: 3.4
Classifier: Programming Language :: Python :: 3.5
Classifier: Framework :: Django
Classifier: Development Status :: 5 - Production/Stable
